fms_sdk/__init__.py
fms_sdk/_version.py
fms_sdk/entity/__init__.py
fms_sdk/model/__init__.py
ipa_fms-0.0.1.dist-info/METADATA
ipa_fms-0.0.1.dist-info/WHEEL
ipa_fms-0.0.1.dist-info/top_level.txt
ipa_fms-0.0.1.dist-info/RECORD
