Metadata-Version: 2.4
Name: ipa-fms
Version: 0.0.1
Summary: template python project with necessary configurations
Author-email: xdewx <present150608@sina.com>
Requires-Python: >=3.10
Requires-Dist: alembic>=1.17.2
Requires-Dist: fastapi[standard]>=0.128.0
Requires-Dist: ipa-python-kit>=0.0.7
Requires-Dist: sqlmodel>=0.0.31
Requires-Dist: typer>=0.20.0
Requires-Dist: typing-extensions>=4.15.0
